propano/__init__.py
propano/anomaly_detector.py
propano/cli.py
propano/utils.py
propano/visualization.py
propano-0.1.2.dist-info/LICENSE
propano-0.1.2.dist-info/METADATA
propano-0.1.2.dist-info/WHEEL
propano-0.1.2.dist-info/entry_points.txt
propano-0.1.2.dist-info/top_level.txt
propano-0.1.2.dist-info/RECORD
